[
  {
    "Hochschule": "Akademie der Bildenden Künste München",
    "Straße": "Akademiestrasse 2-4",
    "PLZ": 80799,
    "Ort": "München",
    "Latitude": "48.153131",
    "Longitude": "11.579151"
  },
  {
    "Hochschule": "AMD Akademie Mode & Design",
    "Straße": "Infanteriestraße 11a",
    "PLZ": 80797,
    "Ort": "München",
    "Latitude": "48.158961",
    "Longitude": "11.554124"
  },
  {
    "Hochschule": "Campus M21",
    "Straße": "Dachauer Straße 124",
    "PLZ": 80637,
    "Ort": "München",
    "Latitude": "48.162400",
    "Longitude": "11.543940"
  },
  {
    "Hochschule": "Fachhochschule für öffentliche Verwaltung und Rechtspflege in Bayern",
    "Straße": "Wagmüllerstraße 20",
    "PLZ": 80539,
    "Ort": "München",
    "Latitude": "48.142370",
    "Longitude": "11.588674"
  },
  {
    "Hochschule": "FOM Hochschule für Oekonomie & Management",
    "Straße": "Arnulfstraße 30",
    "PLZ": 80335,
    "Ort": "München",
    "Latitude": "48.143071",
    "Longitude": "11.555860"
  },
  {
    "Hochschule": "Globe Business College Munich",
    "Straße": "Arnulfstrasse 58",
    "PLZ": 80335,
    "Ort": "München",
    "Latitude": "48.143601",
    "Longitude": "11.549617"
  },
  {
    "Hochschule": "H:G Hochschule für Gesundheit & Sport, Technik & Kunst",
    "Straße": "Steinheilstraße 4",
    "PLZ": 85737,
    "Ort": "Ismaning",
    "Latitude": "48.229130",
    "Longitude": "11.680940"
  },
  {
    "Hochschule": "Hessische Berufsakademie",
    "Straße": "Arnulfstraße 30",
    "PLZ": 80335,
    "Ort": "München",
    "Latitude": "48.143071",
    "Longitude": "11.555860"
  },
  {
    "Hochschule": "Hochschule der Bayerischen Wirtschaft (HDBW)",
    "Straße": "Konrad-Zuse-Platz 8",
    "PLZ": 81829,
    "Ort": "München",
    "Latitude": "48.137490",
    "Longitude": "11.689084"
  },
  {
    "Hochschule": "Hochschule Fresenius",
    "Straße": "Infanteriestraße 11a",
    "PLZ": 80797,
    "Ort": "München",
    "Latitude": "48.158961",
    "Longitude": "11.554124"
  },
  {
    "Hochschule": "Hochschule für Angewandte Sprachen des SDI München",
    "Straße": "Baierbrunner Straße 28",
    "PLZ": 81379,
    "Ort": "München",
    "Latitude": "48.096902",
    "Longitude": "11.531920"
  },
  {
    "Hochschule": "Hochschule für Fernsehen und Film",
    "Straße": "Gabelsbergerstraße 33",
    "PLZ": 80333,
    "Ort": "München",
    "Latitude": "48.150691",
    "Longitude": "11.558942"
  },
  {
    "Hochschule": "Hochschule für Musik und Theater München",
    "Straße": "Arcisstraße 12",
    "PLZ": 80333,
    "Ort": "München",
    "Latitude": "48.146010",
    "Longitude": "11.567310"
  },
  {
    "Hochschule": "Hochschule für Philosophie",
    "Straße": "Kaulbachstraße 31",
    "PLZ": 80539,
    "Ort": "München",
    "Latitude": "48.148820",
    "Longitude": "11.582920"
  },
  {
    "Hochschule": "Hochschule Macromedia, University of Applied Sciences",
    "Straße": "Gollierstraße 4",
    "PLZ": 80339,
    "Ort": "München",
    "Latitude": "48.136030",
    "Longitude": "11.547505"
  },
  {
    "Hochschule": "Hochschule München",
    "Straße": "Lothstraße 34",
    "PLZ": 80335,
    "Ort": "München",
    "Latitude": "48.155114",
    "Longitude": "11.553648"
  },
  {
    "Hochschule": "International School of Management",
    "Straße": "Karlstraße 35",
    "PLZ": 80333,
    "Ort": "München",
    "Latitude": "48.144250",
    "Longitude": "11.561458"
  },
  {
    "Hochschule": "Internationale Berufsakademie der F+U Unternehmensgruppe",
    "Straße": "Dessauer Straße 6",
    "PLZ": 80992,
    "Ort": "München",
    "Latitude": "48.180260",
    "Longitude": "11.530720"
  },
  {
    "Hochschule": "IUBH Duales Studium",
    "Straße": "Berg-am-Laim-Straße 47",
    "PLZ": 81673,
    "Ort": "München",
    "Latitude": "48.131577",
    "Longitude": "11.614875"
  },
  {
    "Hochschule": "Katholische Stiftungsfachhochschule München",
    "Straße": "Preysingstraße 83",
    "PLZ": 81667,
    "Ort": "München",
    "Latitude": "48.131930",
    "Longitude": "11.601630"
  },
  {
    "Hochschule": "Ludwig-Maximilians-Universität München",
    "Straße": "Geschwister-Scholl-Platz 1",
    "PLZ": 80539,
    "Ort": "München",
    "Latitude": "48.150479",
    "Longitude": "11.580015"
  },
  {
    "Hochschule": "Mediadesign Hochschule für Design und Informatik",
    "Straße": "Claudius-Keller-Straße 7",
    "PLZ": 81669,
    "Ort": "München",
    "Latitude": "48.116568",
    "Longitude": "11.603609"
  },
  {
    "Hochschule": "Munich Business School",
    "Straße": "Elsenheimerstraße 61",
    "PLZ": 80687,
    "Ort": "München",
    "Latitude": "48.135976",
    "Longitude": "11.524539"
  },
  {
    "Hochschule": "Technische Universität München",
    "Straße": "Arcisstraße 21",
    "PLZ": 80333,
    "Ort": "München",
    "Latitude": "48.149350",
    "Longitude": "11.567826"
  },
  {
    "Hochschule": "Universität der Bundeswehr München",
    "Straße": "Werner-Heisenberg-Weg 39",
    "PLZ": 85577,
    "Ort": "Neubiberg",
    "Latitude": "48.078538",
    "Longitude": "11.650202"
  }
]